AUTHORS.rst
CONTRIBUTING.rst
HISTORY.rst
LICENSE
MANIFEST.in
README.rst
setup.cfg
setup.py
docs/Makefile
docs/authors.rst
docs/conf.py
docs/contributing.rst
docs/history.rst
docs/index.rst
docs/installation.rst
docs/make.bat
docs/readme.rst
docs/usage.rst
epanetgpt/__init__.py
epanetgpt/epanetgpt.py
epanetgpt.egg-info/PKG-INFO
epanetgpt.egg-info/SOURCES.txt
epanetgpt.egg-info/dependency_links.txt
epanetgpt.egg-info/not-zip-safe
epanetgpt.egg-info/requires.txt
epanetgpt.egg-info/top_level.txt
tests/Net1.inp
tests/Net1.pdf
tests/__init__.py
tests/test_epanetgpt.py
tests/test_example.py