Metadata-Version: 2.1
Name: epanetgpt
Version: 0.1.0
Summary: epanetgpt is a Python package designed to enable users to interact with their EPANET input files through natural language conversations. Inspired by pdfgpt, its objective is to suggest/run code snippets.
Home-page: https://github.com/KIOS-Research/epanetgpt
Author: Marios S. Kyriakou
Author-email: mariosmsk@gmail.com
License: MIT license
Keywords: epanetgpt
Classifier: Development Status :: 2 - Pre-Alpha
Classifier: Intended Audience :: Developers
Classifier: License :: OSI Approved :: MIT License
Classifier: Natural Language :: English
Classifier: Programming Language :: Python :: 3
Classifier: Programming Language :: Python :: 3.6
Classifier: Programming Language :: Python :: 3.7
Classifier: Programming Language :: Python :: 3.8
Requires-Python: >=3.6
License-File: LICENSE
License-File: AUTHORS.rst
